quicksearch/__init__.py
quicksearch/api.py
quicksearch/cli.py
quicksearch/config.py
quicksearch/exceptions.py
quicksearch/logging_config.py
quicksearch/adapters/base.py
quicksearch/adapters/mongodb.py
quicksearch/core/__init__.py
quicksearch/core/engine.py
quicksearch/core/indexer.py
quicksearch/core/orchestrator.py
quicksearch/core/schema.py
quicksearch/core/searcher.py
quicksearch/sync/manager.py
quicksearch_py-1.0.2.dist-info/licenses/LICENSE
quicksearch_py-1.0.2.dist-info/METADATA
quicksearch_py-1.0.2.dist-info/WHEEL
quicksearch_py-1.0.2.dist-info/entry_points.txt
quicksearch_py-1.0.2.dist-info/top_level.txt
quicksearch_py-1.0.2.dist-info/RECORD
