Metadata-Version: 2.4
Name: quicksearch-py
Version: 1.0.2
Summary: A high-performance, pluggable prefix search engine for big data.
Author-email: Poornachandra Hariprasad Kashi <poornakashi@gmail.com>
Requires-Python: >=3.8
License-File: LICENSE
Requires-Dist: whoosh>=2.7.4
Requires-Dist: motor>=3.3.0
Requires-Dist: pydantic>=2.0.0
Requires-Dist: click>=8.0.0
Requires-Dist: tqdm>=4.66.0
Dynamic: license-file
Dynamic: requires-python
